README
setup.py
IPChange/IPChange.py
IPChange/__init__.py
ipchange.egg-info/PKG-INFO
ipchange.egg-info/SOURCES.txt
ipchange.egg-info/dependency_links.txt
ipchange.egg-info/top_level.txt