Metadata-Version: 1.1
Name: ipchange
Version: 0.11
Summary: change ubunt static ip address by manipulating the file /etc/network/interfaces, but you must get the root previlege before to call this lib 
Home-page: http://sourceforge.net/projects/ubuntustaticipchange/
Author: stephon xue
Author-email: nobyte@sina.com
License: BSD
Platform: Linux
Classifier: Development Status :: 5 - Production/Stable
Classifier: License :: OSI Approved :: BSD License
Classifier: Operating System :: POSIX :: Linux
Classifier: Intended Audience :: Developers
Classifier: Programming Language :: Python
Classifier: Topic :: Software Development :: Libraries
Classifier: Topic :: System :: Networking
Classifier: Topic :: System :: Systems Administration
